common/__init__.py
common/src/__init__.py
common/src/timeseries/__init__.py
common/src/timeseries/series_base.py
common/test/__init__.py
common/test/run_test.py
common/test/timeseries/__init__.py
common/test/timeseries/series_base.py
muisca1492_common-0.0.1.dist-info/LICENSE
muisca1492_common-0.0.1.dist-info/METADATA
muisca1492_common-0.0.1.dist-info/WHEEL
muisca1492_common-0.0.1.dist-info/top_level.txt
muisca1492_common-0.0.1.dist-info/RECORD
